exergenics/__init__.py
exergenics/exergenics.py
exergenics-2.13.2.dist-info/METADATA
exergenics-2.13.2.dist-info/WHEEL
exergenics-2.13.2.dist-info/top_level.txt
exergenics-2.13.2.dist-info/RECORD
