Metadata-Version: 2.1
Name: exergenics
Version: 2.13.2
Home-page: https://github.com/Exergenics/internal-portal-api
Author: John Christian
Author-email: john.christian@exergenics.com
Keywords: exergenics portal api
Requires-Python: >=3.8.10
Requires-Dist: boto3
Requires-Dist: datetime
Requires-Dist: requests
Requires-Dist: urllib3
Requires-Dist: logtail-python
Requires-Dist: pytz
Provides-Extra: dev
Requires-Dist: pytest (>=7.0) ; extra == 'dev'
Requires-Dist: twine (>=4.0.2) ; extra == 'dev'
Requires-Dist: bump (==1.3.2) ; extra == 'dev'
